Metadata-Version: 1.1
Name: imagesoup
Version: 0.1.0
Summary: A Python library designed for quick search and downloading images.
Home-page: https://github.com/rafpyprog/ImageSoup
Author: Rafael Alves Ribeiro
Author-email: rafael.alves.ribeiro@gmail.com
License: MIT
Keywords: search image google
Platform: UNKNOWN
Classifier: Development Status :: 4 - Beta
Classifier: Intended Audience :: Developers
Classifier: Programming Language :: Python :: 2.7
Classifier: Programming Language :: Python :: 3.6
Classifier: Topic :: Multimedia :: Graphics
Classifier: Topic :: Internet :: WWW/HTTP :: Indexing/Search
Classifier: License :: OSI Approved :: MIT License
